README.rst
setup.py
admin_cli/__init__.py
admin_cli/apps.py
admin_cli/models.py
admin_cli/settings.py
admin_cli/management/__init__.py
admin_cli/management/commands/__init__.py
admin_cli/management/commands/cli.py
admin_cli/migrations/__init__.py
django_admin_cli.egg-info/PKG-INFO
django_admin_cli.egg-info/SOURCES.txt
django_admin_cli.egg-info/dependency_links.txt
django_admin_cli.egg-info/not-zip-safe
django_admin_cli.egg-info/pbr.json
django_admin_cli.egg-info/top_level.txt
tests/__init__.py
tests/runtests.py
tests/testapp/__init__.py
tests/testapp/admin.py
tests/testapp/forms.py
tests/testapp/models.py
tests/testapp/tests.py
tests/testapp/views.py
tests/testapp/migrations/0001_initial.py
tests/testapp/migrations/__init__.py